{
  "title": "Deutsche Kultur: Feste und Traditionen",
  "text": "Deutschland ist bekannt für seine vielfältigen Feste und Traditionen, die oft tief in der Geschichte verwurzelt sind. Eines der bekanntesten Feste ist das Oktoberfest in München, das jährlich Millionen von Besuchern anzieht. Hier feiern die Menschen mit Bier, traditionellen Speisen und bayerischer Musik. Ein weiteres wichtiges Fest ist Weihnachten, das in Deutschland sehr festlich gefeiert wird. Viele Städte haben Weihnachtsmärkte, wo man Geschenke kaufen und typische Leckereien wie Lebkuchen und Glühwein genießen kann. \n\nEin weiteres Beispiel für eine deutsche Tradition ist der Karneval, der vor der Fastenzeit gefeiert wird. Besonders in Städten wie Köln und Düsseldorf gibt es farbenfrohe Umzüge und viele Menschen verkleiden sich. Diese Feste zeigen die Vielfalt der deutschen Kultur und bringen die Menschen zusammen. In Deutschland ist es üblich, diese Traditionen zu pflegen und an ihnen teilzunehmen, um die Gemeinschaft zu stärken. Das Verständnis und die Wertschätzung dieser Feste sind wichtig für alle, die die deutsche Sprache und Kultur lernen möchten.",
  "date": "2026-03-21T10:48:27.269959+00:00",
  "category": "culture",
  "vocabs": [
    {
      "word": "vielfältig",
      "definition": "diverse or varied"
    },
    {
      "word": "verankert",
      "definition": "anchored or rooted"
    },
    {
      "word": "anziehen",
      "definition": "to attract"
    },
    {
      "word": "festlich",
      "definition": "festive"
    },
    {
      "word": "Leckereien",
      "definition": "treats or delicacies"
    },
    {
      "word": "Karneval",
      "definition": "carnival"
    },
    {
      "word": "farbenfroh",
      "definition": "colorful"
    },
    {
      "word": "verkleiden",
      "definition": "to dress up"
    },
    {
      "word": "Gemeinschaft",
      "definition": "community"
    },
    {
      "word": "pflegen",
      "definition": "to maintain or cultivate"
    },
    {
      "word": "Wertschätzung",
      "definition": "appreciation"
    },
    {
      "word": "Teilnehmen",
      "definition": "to participate"
    },
    {
      "word": "Traditionen",
      "definition": "traditions"
    },
    {
      "word": "Umzüge",
      "definition": "parades"
    },
    {
      "word": "Bier",
      "definition": "beer"
    }
  ],
  "voice_path": "lessons/latest.mp3"
}