{
  "title": "Die Weimarer Republik",
  "text": "Die Weimarer Republik war die erste demokratische Regierung in Deutschland nach dem Ersten Weltkrieg. Sie wurde 1919 gegründet und dauerte bis 1933. Die Republik erhielt ihren Namen von der Stadt Weimar, wo die Verfassung ausgearbeitet wurde. Die Weimarer Republik war eine Zeit großer politischer und wirtschaftlicher Schwierigkeiten. Die Hyperinflation von 1923 führte dazu, dass die Menschen ihre Ersparnisse verloren. Trotz dieser Probleme gab es auch kulturelle Blüten. Die 1920er Jahre waren bekannt für Fortschritte in Kunst, Literatur und Wissenschaft. Berühmte Persönlichkeiten wie der Schriftsteller Thomas Mann und der Regisseur Fritz Lang prägten diese Zeit. Politisch war die Weimarer Republik von Instabilität geprägt. Verschiedene Parteien kämpften um die Macht, und es gab oft Regierungswechsel. 1933 endete die Weimarer Republik mit der Machtergreifung der Nationalsozialisten unter Adolf Hitler. Diese Zeit ist wichtig, um die Entwicklung der deutschen Demokratie zu verstehen und die Gefahren extremistischen Denkens zu erkennen.",
  "date": "2026-03-21T06:28:11.702159+00:00",
  "category": "history",
  "vocabs": [
    {
      "word": "Weimarer Republik",
      "definition": "Weimar Republic, the first democratic government in Germany."
    },
    {
      "word": "Hyperinflation",
      "definition": "Hyperinflation, extreme rapid inflation that devalues currency."
    },
    {
      "word": "Verfassung",
      "definition": "Constitution, a set of fundamental principles governing a state."
    },
    {
      "word": "kulturelle Blüten",
      "definition": "Cultural bloom, a period of significant artistic and cultural development."
    },
    {
      "word": "Stabilität",
      "definition": "Stability, the state of being stable or steady."
    },
    {
      "word": "Instabilität",
      "definition": "Instability, lack of stability; a state of unpredictability."
    },
    {
      "word": "Machtergreifung",
      "definition": "Seizure of power, the act of gaining control over a government."
    },
    {
      "word": "extremistisches Denken",
      "definition": "Extremist thinking, belief in radical ideologies."
    },
    {
      "word": "Ersparnisse",
      "definition": "Savings, money that has been saved over time."
    },
    {
      "word": "Regierungswechsel",
      "definition": "Change of government, a shift in political leadership."
    },
    {
      "word": "Persönlichkeiten",
      "definition": "Personalities, notable individuals with significant influence."
    },
    {
      "word": "literarisch",
      "definition": "Literary, related to literature or authorship."
    },
    {
      "word": "wissenschaftlich",
      "definition": "Scientific, pertaining to science or its methodologies."
    }
  ],
  "voice_path": "lessons/latest.mp3"
}